django_unixdatetimefield/__init__.py
django_unixdatetimefield/fields.py
django_unixdatetimefield/models.py
django_unixdatetimefield/tests/__init__.py
django_unixdatetimefield/tests/models.py
django_unixdatetimefield/tests/tests.py
django_unixdatetimefield-1.0.3.dist-info/DESCRIPTION.rst
django_unixdatetimefield-1.0.3.dist-info/METADATA
django_unixdatetimefield-1.0.3.dist-info/RECORD
django_unixdatetimefield-1.0.3.dist-info/WHEEL
django_unixdatetimefield-1.0.3.dist-info/metadata.json
django_unixdatetimefield-1.0.3.dist-info/top_level.txt
