Metadata-Version: 2.0
Name: django-unixdatetimefield
Version: 1.0.3
Summary: UnixDateTimeField in Django
Home-page: https://github.com/Niklas9/django-unixdatetimefield
Author: Niklas Andersson
Author-email: nandersson900@gmail.com
License: UNKNOWN
Platform: UNKNOWN
Classifier: Framework :: Django
Classifier: Intended Audience :: Developers
Classifier: Intended Audience :: System Administrators
Classifier: Operating System :: OS Independent
Classifier: Topic :: Software Development
Requires-Dist: django
